{
  "backup_data_uid": "b28273356e4b90a9", 
  "data_name": "fai-pep", 
  "no_compile": "yes", 
  "no_target_file": "yes", 
  "only_for_target_os_tags": [
    "linux"
  ], 
  "program": "yes", 
  "process_in_tmp": "yes", 
  "run_cmds": {
    "shufflenet": {
      "run_deps": {
        "bench-fai-pep": {
          "local": "yes", 
          "name": "FAI-PEP AI benchmark", 
          "sort": 20, 
          "tags": "bench,fai-pep"
        }, 
        "python": {
          "local": "yes", 
          "name": "Python", 
          "sort": 10, 
          "tags": "compiler,python"
        }
      }, 
      "run_time": {
        "run_cmd_main": "../ck_run_shufflenet.sh"
      }
    }
  }, 
  "tags": [
    "fai-pep"
  ]
}
